AffinitySvgPatcher/AffinitySvgPatcher.py
AffinitySvgPatcher/__init__.py
AffinitySvgPatcher/__main__.py
AffinitySvgPatcher/py.typed
AffinitySvgPatcher-1.0.0.dist-info/LICENSE
AffinitySvgPatcher-1.0.0.dist-info/METADATA
AffinitySvgPatcher-1.0.0.dist-info/WHEEL
AffinitySvgPatcher-1.0.0.dist-info/entry_points.txt
AffinitySvgPatcher-1.0.0.dist-info/top_level.txt
AffinitySvgPatcher-1.0.0.dist-info/RECORD
