Metadata-Version: 2.1
Name: AffinitySvgPatcher
Version: 1.0.0
Summary: A module for patching matplotlib-generated SVG files to make them work Affinity Designer.
Author: Lorenzo Peri
License: GNU GENERAL PUBLIC LICENSE
Project-URL: Homepage, https://https://github.com/LorenzoPeri17/AffinitySvgPatcher
Requires-Python: >=3.9
License-File: LICENSE
